src/__init__.py
textoir-0.0.5.dist-info/METADATA
textoir-0.0.5.dist-info/RECORD
textoir-0.0.5.dist-info/WHEEL
textoir-0.0.5.dist-info/top_level.txt
